Matplot_addons/Addons.py
Matplot_addons/__init__.py
Matplot_addons-0.0.4.dist-info/METADATA
Matplot_addons-0.0.4.dist-info/WHEEL
Matplot_addons-0.0.4.dist-info/top_level.txt
Matplot_addons-0.0.4.dist-info/RECORD
