Metadata-Version: 2.1
Name: Matplot-addons
Version: 0.0.4
Summary: Matplotlib addons for simplify life
Home-page: https://github.com/Sergiodeavilac
Author: Sergio de Avila
Author-email: sergiodeavilacabral@gmail.com
License: GPL-3.0
Requires-Dist: matplotlib
